{
    "url": "https://wwwk.kangwon.ac.kr/www/selectBbsNttView.do?bbsNo=58&nttNo=99936&&pageUnit=10&key=313&pageIndex=9",
    "id": "99936",
    "title": "5공학관, 학생회관 식당 손소독기 문의",
    "timestamp": "1073",
    "poster": "5공학관과 학생회관 식당에 위치한 손소독기가 작동하지 않습니다. 수리부탁드립니다. 감사합니다. function fn_resize_tbody() { tw = $('#contents').width(); if(tw) { rw = tw - 35; $('#ntt_cn_wdv').css('width', rw+'px'); } } $(document).ready(function() { fn_resize_tbody(); var link_window = $('#bbs_ntt_cn_con'); $(link_window).html( link_window.html().autoLink({ target: \"_blank\" }) ); }); $(window).resize(function() { fn_resize_tbody(); });",
    "content": ""
}